{"cameraMode":{"drawMode":0,"name":"Shaded","section":"Shading Mode"},"sceneLighting":false,"audioPlay":false,"sceneViewState":{"m_AlwaysRefresh":false,"showFog":true,"showSkybox":false,"showFlares":true,"showImageEffects":true,"showParticleSystems":true,"showVisualEffectGraphs":true,"m_FxEnabled":true},"in2DMode":false,"pivot":{"x":0.8859391808509827,"y":-0.24231187999248506,"z":-0.3629630506038666},"rotation":{"x":-0.18047158420085908,"y":-0.39329761266708376,"z":0.07903216779232025,"w":-0.8980896472930908},"size":1.3139618635177613,"orthographic":false}