{"cameraMode":{"drawMode":0,"name":"Shaded","section":"Shading Mode"},"sceneLighting":true,"audioPlay":false,"sceneViewState":{"m_AlwaysRefresh":false,"showFog":false,"showSkybox":true,"showFlares":true,"showImageEffects":true,"showParticleSystems":true,"showVisualEffectGraphs":true,"m_FxEnabled":true},"in2DMode":false,"pivot":{"x":-2.9622890949249269,"y":6.323503494262695,"z":0.1745842844247818},"rotation":{"x":0.0145587008446455,"y":0.9671910405158997,"z":-0.2474704086780548,"w":0.0563148558139801},"size":1.7660253047943116,"orthographic":false}